rebulk/__init__.py
rebulk/__version__.py
rebulk/builder.py
rebulk/chain.py
rebulk/debug.py
rebulk/formatters.py
rebulk/introspector.py
rebulk/loose.py
rebulk/match.py
rebulk/pattern.py
rebulk/processors.py
rebulk/rebulk.py
rebulk/remodule.py
rebulk/rules.py
rebulk/toposort.py
rebulk/utils.py
rebulk/validators.py
rebulk/test/__init__.py
rebulk/test/default_rules_module.py
rebulk/test/rebulk_rules_module.py
rebulk/test/rules_module.py
rebulk/test/test_chain.py
rebulk/test/test_debug.py
rebulk/test/test_introspector.py
rebulk/test/test_loose.py
rebulk/test/test_match.py
rebulk/test/test_pattern.py
rebulk/test/test_processors.py
rebulk/test/test_rebulk.py
rebulk/test/test_rules.py
rebulk/test/test_toposort.py
rebulk/test/test_validators.py
rebulk-3.2.0.dist-info/LICENSE
rebulk-3.2.0.dist-info/METADATA
rebulk-3.2.0.dist-info/WHEEL
rebulk-3.2.0.dist-info/top_level.txt
rebulk-3.2.0.dist-info/zip-safe
rebulk-3.2.0.dist-info/RECORD
