Metadata-Version: 2.1
Name: rebulk
Version: 3.2.0
Summary: Rebulk - Define simple search patterns in bulk to perform advanced matching on any string.
Home-page: https://github.com/Toilal/rebulk/
Download-URL: https://pypi.python.org/packages/source/r/rebulk/rebulk-3.2.0.tar.gz
Author: Rémi Alvergnat
Author-email: toilal.dev@gmail.com
License: MIT
Keywords: re regexp regular expression search pattern string match
Classifier: Development Status :: 5 - Production/Stable
Classifier: License :: OSI Approved :: MIT License
Classifier: Operating System :: OS Independent
Classifier: Intended Audience :: Developers
Classifier: Programming Language :: Python :: 3
Classifier: Programming Language :: Python :: 3.7
Classifier: Programming Language :: Python :: 3.8
Classifier: Programming Language :: Python :: 3.9
Classifier: Programming Language :: Python :: 3.10
Classifier: Programming Language :: Python :: 3.11
Classifier: Topic :: Software Development :: Libraries :: Python Modules
Provides-Extra: test
Provides-Extra: dev
Provides-Extra: native
License-File: LICENSE
